automait/__init__.py
automait/client.py
automait-0.0.8.dist-info/LICENSE
automait-0.0.8.dist-info/METADATA
automait-0.0.8.dist-info/WHEEL
automait-0.0.8.dist-info/top_level.txt
automait-0.0.8.dist-info/RECORD
