Metadata-Version: 2.1
Name: automait
Version: 0.0.8
Summary: automait package for interfacing our modeling services
Home-page: https://gitlab.com/automait_public/automait_client
Author: Lukas Leuschen
Author-email: lukas.leuschen@automait.ai
Project-URL: Bug Tracker, https://gitlab.com/automait_public/automait_client/-/issues
Classifier: Programming Language :: Python :: 3
Classifier: License :: OSI Approved :: GNU General Public License v3 (GPLv3)
Classifier: Operating System :: OS Independent
Requires-Python: >=3.6
License-File: LICENSE
